otter_api_wrapper/__init__.py
otter_api_wrapper/core.py
otter_api_wrapper/utils.py
otter_api_wrapper-0.0.3.dist-info/LICENSE
otter_api_wrapper-0.0.3.dist-info/METADATA
otter_api_wrapper-0.0.3.dist-info/WHEEL
otter_api_wrapper-0.0.3.dist-info/top_level.txt
otter_api_wrapper-0.0.3.dist-info/RECORD
