Metadata-Version: 2.1
Name: otter_api_wrapper
Version: 0.0.3
Summary: This is a Python wrapper for the Otter API. This wrapper helps you run the API available at https://otter.ccm.sickkids.ca/.
Author-email: "Pedro L. Ballester" <pedro.lemosballester@sickkids.ca>
Project-URL: Homepage, https://otter.ccm.sickkids.ca
Project-URL: Issues, https://github.com/shlienlab/otter-api-wrapper/issues
Classifier: Programming Language :: Python :: 3
Classifier: Operating System :: OS Independent
Requires-Python: >=3.7
License-File: LICENSE
